<?xml version="1.0" encoding="UTF-8"?>
<RetrieveValueSetResponse xmlns="urn:ihe:iti:svs:2008"
                          xmlns:xsi="http://www.w3.org/2001/XMLSchema-instance"
                          xsi:schemaLocation="urn:ihe:iti:svs:2008">
   <ValueSet displayName="JDV_QuantiteLA_CISIS"
             id="1.2.250.1.213.1.1.5.747"
             revisionDate="2023-08-03T00:00:00"
             version="test">
      <ConceptList>
         <Concept code="O40"
                  codeSystem="2.16.840.1.113883.6.3"
                  dateFin=""
                  dateValid="20230803000000"
                  displayName="Hydramnios"/>
         <Concept code="O41.0"
                  codeSystem="2.16.840.1.113883.6.3"
                  dateFin=""
                  dateValid="20230803000000"
                  displayName="Oligoamnios"/>
         <Concept code="278092006"
                  codeSystem="2.16.840.1.113883.6.96"
                  dateFin=""
                  dateValid="20230803000000"
                  displayName="volume de liquide amniotique dans l'intervalle de référence"/>
         <Concept code="289297007"
                  codeSystem="2.16.840.1.113883.6.96"
                  dateFin=""
                  dateValid="20230803000000"
                  displayName="liquide amniotique absent"/>
      </ConceptList>
   </ValueSet>
</RetrieveValueSetResponse>
